mask_plasmid/__init__.py
mask_plasmid/run_mask_plasmid.py
mask_plasmid-0.1.8.dist-info/AUTHORS
mask_plasmid-0.1.8.dist-info/LICENSE
mask_plasmid-0.1.8.dist-info/METADATA
mask_plasmid-0.1.8.dist-info/WHEEL
mask_plasmid-0.1.8.dist-info/entry_points.txt
mask_plasmid-0.1.8.dist-info/pbr.json
mask_plasmid-0.1.8.dist-info/top_level.txt
mask_plasmid-0.1.8.dist-info/RECORD
