Metadata-Version: 2.1
Name: mask-plasmid
Version: 0.1.8
Summary: Configurable retrying.
Home-page: https://github.com/andersgs/mask_plasmid
Author: Anders Goncalves da Silva
Author-email: andersgs@gmail.com
License: UNKNOWN
Platform: UNKNOWN
Classifier: Topic :: Scientific/Engineering :: Bio-Informatics
Classifier: Programming Language :: Python :: 3.6
Classifier: Programming Language :: Python :: 3.7
Classifier: License :: OSI Approved :: GNU General Public License v3 (GPLv3)
Requires-Python: >=3.6
Requires-Dist: biopython (>=1.72)
Requires-Dist: click (>=7)
